vsmask/__init__.py
vsmask/_metadata.py
vsmask/py.typed
vsmask/types.py
vsmask/util.py
vsmask/edge/_1d.py
vsmask/edge/_2x2.py
vsmask/edge/_3x3.py
vsmask/edge/_5x5.py
vsmask/edge/__init__.py
vsmask/edge/_abstract.py
vsmask/edge/_misc.py
vsmask-0.5.1.dist-info/LICENSE
vsmask-0.5.1.dist-info/METADATA
vsmask-0.5.1.dist-info/WHEEL
vsmask-0.5.1.dist-info/top_level.txt
vsmask-0.5.1.dist-info/RECORD
