Metadata-Version: 2.1
Name: vsmask
Version: 0.5.1
Summary: Various masking tools for Vapoursynth
Author: Irrational Encoding Wizardry
Author-email: wizards@encode.moe
Maintainer: Ichunjo
Maintainer-email: wizards@encode.moe
Project-URL: Source Code, https://github.com/Irrational-Encoding-Wizardry/vs-mask
Project-URL: Documentation, https://vsmask.encode.moe/en/latest/
Project-URL: Contact, https://discord.gg/qxTxVJGtst
Classifier: Programming Language :: Python :: 3
Classifier: License :: OSI Approved :: MIT License
Classifier: Operating System :: OS Independent
Requires-Python: >=3.10
License-File: LICENSE
Requires-Dist: VapourSynth (>=60)
Requires-Dist: vsutil (~=0.8.0)
